{
  "version": "1.0",
  "chapters": [
    {
      "title": "NCC",
      "wing": "COMMON",
      "sections": [
        {
          "name": "General",
          "difficulty": [
            "JD/JW",
            "SD/SW"
          ],
          "topics": [
            "History and formation of NCC",
            "Aims and objectives of NCC",
            "NCC motto and pledge",
            "Organization structure"
          ],
          "learning_objectives": [
            "Understanding NCC's role in nation building",
            "Knowledge of NCC history and evolution",
            "Comprehension of NCC values and principles"
          ],
          "content": "The National Cadet Corps (NCC) is a youth development movement in India that aims to instill discipline, leadership, and a spirit of service among young citizens. This section covers the history, formation, aims, objectives, motto, pledge, and organizational structure of the NCC, highlighting its role in nation-building and the values it promotes.",
          "keywords": [
            "ncc",
            "history",
            "formation",
            "aims",
            "objectives",
            "motto",
            "pledge",
            "organization",
            "nation-building",
            "values",
            "principles"
          ],
          "page_number": 13
        },
        {
          "name": "Organisation",
          "difficulty": [
            "JD/JW",
            "SD/SW"
          ],
          "topics": [
            "NCC organizational hierarchy",
            "Command structure",
            "Units and formations",
            "Administrative setup"
          ],
          "learning_objectives": [
            "Understanding organizational structure",
            "Knowledge of command hierarchy",
            "Awareness of administrative processes"
          ],
          "content": "This section explains the NCC's organizational hierarchy, command structure, units, formations, and administrative setup. It provides insights into how the NCC is structured and managed at various levels.",
          "keywords": [
            "organizational hierarchy",
            "command structure",
            "units",
            "formations",
            "administrative setup",
            "ncc structure"
          ],
          "page_number": 14
        },
        {
          "name": "Philosophy of Training",
          "difficulty": [
            "JD/JW",
            "SD/SW"
          ],
          "topics": [
            "Training methodology",
            "Character development principles",
            "Leadership development approach",
            "Discipline and values"
          ],
          "learning_objectives": [
            "Understanding training philosophy",
            "Appreciation of character building",
            "Knowledge of leadership principles"
          ],
          "content": "This section introduces the philosophy behind NCC training, focusing on methodologies for character development, leadership, discipline, and the inculcation of values. It emphasizes the importance of a structured and progressive approach to cadet training.",
          "keywords": [
            "training philosophy",
            "character development",
            "leadership",
            "discipline",
            "training methodology",
            "values"
          ],
          "page_number": 14
        },
        {
          "name": "NCC Song",
          "difficulty": [
            "JD/JW",
            "SD/SW"
          ],
          "topics": [
            "NCC song lyrics",
            "Meaning and significance",
            "Proper rendering",
            "Occasions for singing"
          ],
          "learning_objectives": [
            "Memorization of NCC song",
            "Understanding its significance",
            "Proper presentation skills"
          ],
          "content": "Lyrics, meaning, and significance of the NCC song 'Hum Sab Bharatiya Hain', including when and how it should be rendered.",
          "keywords": [
            "singing",
            "memorization",
            "significance",
            "occasions",
            "skills",
            "song",
            "proper",
            "understanding",
            "lyrics",
            "presentation",
            "rendering",
            "meaning"
          ],
          "page_number": 21
        },
        {
          "name": "Incentives for NCC Cadets",
          "difficulty": [
            "JD/JW",
            "SD/SW"
          ],
          "topics": [
            "Academic benefits",
            "Career advantages",
            "Certificate benefits",
            "Selection preferences"
          ],
          "learning_objectives": [
            "Knowledge of available incentives",
            "Understanding career benefits",
            "Motivation for participation"
          ],
          "content": "Details various incentives available to NCC cadets, including academic benefits, career advantages, certificate benefits, and preferences in selections for different services.",
          "keywords": [
            "motivation",
            "certificate",
            "preferences",
            "benefits",
            "incentives",
            "selection",
            "understanding",
            "advantages",
            "academic",
            "knowledge",
            "participation",
            "available",
            "career"
          ],
          "page_number": 23
        }
      ],
      "id": "ncc"
    },
    {
      "title": "NATIONAL INTEGRATION",
      "wing": "COMMON",
      "sections": [
        {
          "name": "Indian History and Culture",
          "difficulty": [
            "JD/JW",
            "SD/SW"
          ],
          "topics": [
            "Ancient Indian civilization",
            "Medieval period",
            "Freedom struggle",
            "Cultural heritage"
          ],
          "learning_objectives": [
            "Understanding Indian heritage",
            "Knowledge of historical events",
            "Appreciation of cultural diversity"
          ],
          "content": "This section explores India's rich history and cultural heritage, covering ancient and medieval civilizations, important historical events, and the struggle for freedom. It highlights the diversity and unique traditions that have shaped Indian society.",
          "keywords": [
            "indian history",
            "cultural heritage",
            "ancient civilization",
            "medieval period",
            "historical events",
            "freedom struggle",
            "diversity"
          ],
          "page_number": 49
        },
        {
          "name": "Religion and Customs of India",
          "difficulty": [
            "JD/JW",
            "SD/SW"
          ],
          "topics": [
            "Major religions in India",
            "Religious festivals",
            "Traditional customs",
            "Cultural practices"
          ],
          "learning_objectives": [
            "Understanding religious diversity",
            "Respect for all religions",
            "Knowledge of customs and traditions"
          ],
          "content": "This section provides an overview of the major religions, festivals, customs, and cultural practices of India. It emphasizes the importance of respecting all religions and understanding the country's diverse traditions.",
          "keywords": [
            "religions of india",
            "religious festivals",
            "customs",
            "cultural practices",
            "traditions",
            "religious diversity"
          ],
          "page_number": 55
        },
        {
          "name": "Unity in Diversity",
          "difficulty": [
            "JD/JW",
            "SD/SW"
          ],
          "topics": [
            "Concept of unity in diversity",
            "Regional variations",
            "Language diversity",
            "Cultural synthesis"
          ],
          "learning_objectives": [
            "Understanding India's diversity",
            "Appreciation of unity concept",
            "Tolerance and acceptance"
          ],
          "content": "Focusing on the idea of 'unity in diversity,' this section discusses India's regional, linguistic, and cultural variations and how they come together to form a unified nation. It promotes tolerance, acceptance, and appreciation of differences.",
          "keywords": [
            "unity in diversity",
            "regional variations",
            "language diversity",
            "cultural synthesis",
            "tolerance",
            "acceptance"
          ],
          "page_number": 58
        },
        {
          "name": "National Integration and its Importance",
          "difficulty": [
            "JD/JW",
            "SD/SW"
          ],
          "topics": [
            "Meaning of national integration",
            "Importance for nation building",
            "Challenges to integration",
            "Role of youth"
          ],
          "learning_objectives": [
            "Understanding national integration",
            "Recognizing its importance",
            "Commitment to national unity"
          ],
          "content": "This section explains the concept and significance of national integration for India's progress. It covers the challenges to integration, the importance of unity, and the vital role played by youth in nation-building.",
          "keywords": [
            "national integration",
            "nation building",
            "unity",
            "challenges",
            "role of youth"
          ],
          "page_number": 61
        },
        {
          "name": "Famous Leaders of India",
          "difficulty": [
            "JD/JW"
          ],
          "topics": [
            "Mahatma Gandhi - life and principles",
            "Bhagat Singh - sacrifice and patriotism",
            "Lal Bahadur Shastri - simplicity and honesty",
            "Chander Sekhar Azad - revolutionary spirit",
            "Subash Chandra Bose - leadership and courage",
            "Swami Vivekanand - spiritual leadership",
            "Jawaharlal Nehru - modern India's architect",
            "Maulana Abul Kalam Azad - education and unity",
            "Sardar Vallabh Bhai Patel - iron man of India"
          ],
          "learning_objectives": [
            "Knowledge of great leaders",
            "Understanding their contributions",
            "Drawing inspiration from their lives"
          ],
          "content": "Profiles of eminent Indian leaders such as Mahatma Gandhi, Bhagat Singh, Subash Chandra Bose, and others, highlighting their contributions and principles to inspire cadets.",
          "keywords": [
            "inspiration",
            "from",
            "maulana",
            "iron",
            "bhai",
            "bose",
            "leaders",
            "mahatma",
            "spirit",
            "contributions",
            "swami",
            "simplicity",
            "chander",
            "sekhar",
            "subash",
            "gandhi",
            "bhagat singh",
            "lal bahadur shastri",
            "chander sekhar azad",
            "subash chandra bose",
            "swami vivekanand",
            "jawaharlal nehru",
            "maulana abul kalam azad",
            "sardar vallabh bhai patel",
            "leadership",
            "freedom",
            "patriotism",
            "values",
            "principles"
          ],
          "page_number": 64
        },
        {
          "name": "India and Its Neighbours",
          "difficulty": [
            "JD/JW"
          ],
          "topics": [
            "Neighboring countries",
            "Diplomatic relations",
            "Cultural connections",
            "Trade and cooperation"
          ],
          "learning_objectives": [
            "Knowledge of regional geography",
            "Understanding international relations",
            "Awareness of neighborhood policy"
          ],
          "content": "This section examines India's relationships with its neighboring countries, focusing on diplomatic ties, cultural connections, regional cooperation, and trade. It aims to build awareness of India's neighborhood policy and international relations.",
          "keywords": [
            "india neighbours",
            "diplomatic relations",
            "cultural connections",
            "regional cooperation",
            "trade",
            "neighborhood policy"
          ],
          "page_number": 91
        },
        {
          "name": "Contribution of Youth in National Building",
          "difficulty": [
            "JD/JW",
            "SD/SW"
          ],
          "topics": [
            "Role of youth in development",
            "Youth movements in India",
            "Social service activities",
            "Nation building initiatives"
          ],
          "learning_objectives": [
            "Understanding youth responsibility",
            "Motivation for social service",
            "Commitment to nation building"
          ],
          "content": "This section discusses the significant role of youth in national development, highlighting youth movements, social service activities, and initiatives that contribute to nation building.",
          "keywords": [
            "youth in nation building",
            "youth movements",
            "social service",
            "national development",
            "responsibility"
          ],
          "page_number": null
        },
        {
          "name": "Nation State, National Interests and Objectives",
          "difficulty": [
            "SD/SW"
          ],
          "topics": [
            "Concept of nation state",
            "National interests",
            "National objectives",
            "Policy formulation"
          ],
          "learning_objectives": [
            "Understanding political concepts",
            "Knowledge of national interests",
            "Awareness of policy objectives"
          ],
          "content": "This section explains the concept of the nation state, national interests, and objectives. It also covers the process of policy formulation and the importance of understanding political concepts for national progress.",
          "keywords": [
            "nation state",
            "national interests",
            "national objectives",
            "policy formulation",
            "political concepts"
          ],
          "page_number": 103
        }
      ],
      "id": "national-integration"
    },
    {
      "title": "FOOT DRILL",
      "wing": "COMMON",
      "sections": [
        {
          "name": "General and Words of Command",
          "difficulty": [
            "JD/JW",
            "SD/SW"
          ],
          "topics": [
            "Purpose of drill",
            "Types of commands",
            "Voice and manner",
            "Basic positions"
          ],
          "learning_objectives": [
            "Understanding drill importance",
            "Proper command execution",
            "Developing discipline"
          ],
          "content": "Introduction to drill, its purpose, types of commands, proper voice modulation, manner of giving commands, and basic drill positions.",
          "keywords": [
            "positions",
            "basic",
            "execution",
            "discipline",
            "manner",
            "commands",
            "purpose",
            "developing",
            "proper",
            "understanding",
            "importance",
            "drill",
            "types",
            "voice",
            "command"
          ],
          "page_number": 108
        },
        {
          "name": "Attention, Stand at Ease and Stand Easy, Turning and Inclining at the Halt",
          "difficulty": [
            "JD/JW",
            "SD/SW"
          ],
          "topics": [
            "Position of attention",
            "Stand at ease position",
            "Stand easy position",
            "Right/left turn",
            "About turn"
          ],
          "learning_objectives": [
            "Mastering basic positions",
            "Proper turning movements",
            "Developing precision"
          ],
          "content": "Detailed explanation and practice of fundamental drill positions like Attention (Savdhan), Stand at Ease (Vishram), Stand Easy, and movements like turning and inclining at the halt.",
          "keywords": [
            "positions",
            "position",
            "basic",
            "attention",
            "turning",
            "precision",
            "turn",
            "developing",
            "easy",
            "ease",
            "mastering",
            "proper",
            "movements",
            "about",
            "stand",
            "right/left"
          ],
          "page_number": 112
        },
        {
          "name": "Sizing, Forming up in Three Ranks, Numbering and Close Order March and Dressing",
          "difficulty": [
            "JD/JW",
            "SD/SW"
          ],
          "topics": [
            "Height-wise arrangement",
            "Three rank formation",
            "Numbering system",
            "Dressing and covering"
          ],
          "learning_objectives": [
            "Understanding formations",
            "Proper alignment",
            "Team coordination"
          ],
          "content": "Procedures for sizing cadets, forming up in three ranks, numbering within the squad, and maintaining proper dressing and covering in close order march.",
          "keywords": [
            "three",
            "team",
            "arrangement",
            "rank",
            "coordination",
            "proper",
            "understanding",
            "alignment",
            "system",
            "formations",
            "covering",
            "formation",
            "dressing",
            "numbering",
            "height-wise"
          ],
          "page_number": 116
        },
        {
          "name": "Saluting at the Halt, Getting on Parade, Falling Out and Dismissing",
          "difficulty": [
            "JD/JW",
            "SD/SW"
          ],
          "topics": [
            "Hand salute technique",
            "Parade procedures",
            "Falling out drill",
            "Dismissal commands"
          ],
          "learning_objectives": [
            "Proper saluting technique",
            "Parade discipline",
            "Ceremonial procedures"
          ],
          "content": "This section covers the correct technique for saluting at the halt, procedures for getting on parade, and the proper way to fall out and dismiss. Emphasis is placed on ceremonial discipline and parade etiquette.",
          "keywords": [
            "saluting technique",
            "parade procedures",
            "falling out",
            "dismissal commands",
            "ceremonial discipline"
          ],
          "page_number": 119
        },
        {
          "name": "Marching: Length of Pace and Time of Marching, Marching in Quick Time and Halt, Slow March and Halt",
          "difficulty": [
            "JD/JW",
            "SD/SW"
          ],
          "topics": [
            "Standard pace length",
            "Marching cadence",
            "Quick time march",
            "Slow march",
            "Halt commands"
          ],
          "learning_objectives": [
            "Proper marching technique",
            "Maintaining cadence",
            "Coordinated movement"
          ],
          "content": "This section explains the standards for pace length and marching cadence, including quick and slow time marching, and the correct methods for halting. It focuses on achieving coordinated movement and maintaining rhythm during drill.",
          "keywords": [
            "marching technique",
            "pace length",
            "cadence",
            "quick time",
            "slow march",
            "halt commands",
            "coordinated movement"
          ],
          "page_number": 123
        },
        {
          "name": "Turning at the March and Wheeling",
          "difficulty": [
            "JD/JW",
            "SD/SW"
          ],
          "topics": [
            "Turning while marching",
            "Wheeling movements",
            "Formation changes",
            "Pivot techniques"
          ],
          "learning_objectives": [
            "Advanced marching skills",
            "Formation coordination",
            "Precise movements"
          ],
          "content": "This section details the methods for turning while on the march and wheeling movements. It covers formation changes, pivot techniques, and the importance of precise coordination during advanced drill maneuvers.",
          "keywords": [
            "turning on march",
            "wheeling",
            "formation changes",
            "pivot techniques",
            "advanced drill"
          ],
          "page_number": 126
        },
        {
          "name": "Saluting at the March",
          "difficulty": [
            "JD/JW",
            "SD/SW"
          ],
          "topics": [
            "Saluting while marching",
            "Eyes right/left",
            "Ceremonial procedures",
            "Timing and coordination"
          ],
          "learning_objectives": [
            "Coordinated saluting",
            "Ceremonial precision",
            "Military courtesy"
          ],
          "content": "This section teaches the correct way to salute while marching, including the 'eyes right/left' command and timing for ceremonial salutes. It emphasizes precision, coordination, and military courtesy.",
          "keywords": [
            "saluting on march",
            "eyes right",
            "ceremonial precision",
            "military courtesy",
            "timing"
          ],
          "page_number": 128
        },
        {
          "name": "Individual Word of Command",
          "difficulty": [
            "JD/JW"
          ],
          "topics": [
            "Personal drill commands",
            "Individual movements",
            "Self-directed drill",
            "Command execution"
          ],
          "learning_objectives": [
            "Independent drill execution",
            "Self-discipline",
            "Command understanding"
          ],
          "content": "This section focuses on individual words of command, self-directed drill, and the development of independent drill execution and self-discipline.",
          "keywords": [
            "individual command",
            "personal drill",
            "self-directed",
            "independent execution",
            "self-discipline"
          ],
          "page_number": null
        },
        {
          "name": "Side Pace, Pace Forward and to the Rear",
          "difficulty": [
            "SD/SW"
          ],
          "topics": [
            "Side stepping",
            "Forward pacing",
            "Rear pacing",
            "Directional movements"
          ],
          "learning_objectives": [
            "Advanced movement skills",
            "Directional control",
            "Precise positioning"
          ],
          "content": "This section explains side pace, forward and rear pacing, and directional movements for advanced drill positioning and control.",
          "keywords": [
            "side pace",
            "forward pacing",
            "rear pacing",
            "directional movement",
            "precise positioning"
          ],
          "page_number": 131
        },
        {
          "name": "Marking Time, Forward Halt in Quick Time and Changing Step",
          "difficulty": [
            "SD/SW"
          ],
          "topics": [
            "Marking time technique",
            "Forward halt execution",
            "Step changing",
            "Rhythm maintenance"
          ],
          "learning_objectives": [
            "Advanced drill techniques",
            "Timing precision",
            "Coordinated movements"
          ],
          "content": "",
          "keywords": [
            "execution",
            "step",
            "forward",
            "techniques",
            "marking",
            "precision",
            "technique",
            "advanced",
            "rhythm",
            "movements",
            "time",
            "drill",
            "maintenance",
            "coordinated",
            "timing",
            "halt",
            "changing"
          ],
          "page_number": 133
        },
        {
          "name": "Formation of Squad and Squad Drill",
          "difficulty": [
            "SD/SW"
          ],
          "topics": [
            "Squad formation",
            "Squad movements",
            "Leadership in drill",
            "Team coordination"
          ],
          "learning_objectives": [
            "Squad leadership",
            "Team drill execution",
            "Formation management"
          ],
          "content": "This section explains the formation of a squad, leadership roles in drill, and the importance of teamwork and coordination in executing squad movements.",
          "keywords": [
            "squad formation",
            "team drill",
            "squad leadership",
            "drill coordination",
            "squad movements"
          ],
          "page_number": 135
        }
      ],
      "id": "foot-drill"
    },
    {
      "title": "DRILL WITH ARMS, CEREMONIAL DRILL",
      "wing": "COMMON",
      "sections": [],
      "id": "drill-with-arms-ceremonial-drill"
    },
    {
      "title": "WEAPON TRAINING",
      "wing": "COMMON",
      "sections": [
        {
          "name": "Characteristics of .22 Rifle, Stripping, Assembling, Care and Cleaning and Sight Setting",
          "difficulty": [
            "JD/JW",
            "SD/SW"
          ],
          "topics": [
            ".22 rifle specifications",
            "Stripping procedure",
            "Assembly technique",
            "Cleaning methods",
            "Sight adjustment"
          ],
          "learning_objectives": [
            "Weapon knowledge",
            "Maintenance skills",
            "Safety practices"
          ],
          "content": "This section covers the characteristics and specifications of the .22 rifle, including stripping, assembling, care, cleaning, and sight setting. Emphasis is placed on weapon maintenance and safety.",
          "keywords": [
            ".22 rifle",
            "weapon maintenance",
            "stripping",
            "assembling",
            "cleaning",
            "sight setting",
            "safety"
          ],
          "page_number": 160
        },
        {
          "name": "Loading/Unloading and Bolt Manipulation",
          "difficulty": [
            "JD/JW",
            "SD/SW"
          ],
          "topics": [
            "Loading procedure",
            "Unloading technique",
            "Bolt operation",
            "Safety protocols"
          ],
          "learning_objectives": [
            "Safe weapon operation",
            "Proper procedures",
            "Safety awareness"
          ],
          "content": "This section covers the procedures for safely loading and unloading the .22 rifle, bolt manipulation, and the importance of following safety protocols during weapon handling.",
          "keywords": [
            "loading",
            "unloading",
            "bolt manipulation",
            "weapon safety",
            "handling procedures"
          ],
          "page_number": 165
        },
        {
          "name": "Lying Position and Hold",
          "difficulty": [
            "JD/JW",
            "SD/SW"
          ],
          "topics": [
            "Prone firing position",
            "Weapon grip",
            "Body position",
            "Stability techniques"
          ],
          "learning_objectives": [
            "Proper firing position",
            "Accuracy improvement",
            "Stability control"
          ],
          "content": "This section explains the correct lying (prone) position for firing, proper weapon grip, body alignment, and techniques for improving accuracy and stability.",
          "keywords": [
            "prone position",
            "firing position",
            "weapon grip",
            "stability",
            "accuracy"
          ],
          "page_number": 167
        },
        {
          "name": "Aiming I Range and Targets",
          "difficulty": [
            "JD/JW"
          ],
          "topics": [
            "Aiming fundamentals",
            "Range procedures",
            "Target types",
            "Distance estimation"
          ],
          "learning_objectives": [
            "Basic aiming skills",
            "Range safety",
            "Target recognition"
          ],
          "content": "This section covers the fundamentals of aiming, range procedures, different types of targets, and distance estimation. It emphasizes safety and target recognition skills.",
          "keywords": [
            "aiming fundamentals",
            "range procedures",
            "target types",
            "distance estimation",
            "safety"
          ],
          "page_number": 170
        },
        {
          "name": "Trigger Control and Firing a Shot",
          "difficulty": [
            "JD/JW",
            "SD/SW"
          ],
          "topics": [
            "Trigger squeeze technique",
            "Breathing control",
            "Shot execution",
            "Follow through"
          ],
          "learning_objectives": [
            "Accurate shooting",
            "Trigger control",
            "Consistent technique"
          ],
          "content": "This section explains proper trigger control, breathing techniques, and the steps for firing a shot accurately, including follow-through for consistency.",
          "keywords": [
            "trigger control",
            "breathing technique",
            "firing shot",
            "follow through",
            "shooting accuracy"
          ],
          "page_number": 172
        },
        {
          "name": "Range Procedure and Safety Precautions",
          "difficulty": [
            "JD/JW",
            "SD/SW"
          ],
          "topics": [
            "Range safety rules",
            "Command procedures",
            "Emergency protocols",
            "Equipment handling"
          ],
          "learning_objectives": [
            "Safety consciousness",
            "Range discipline",
            "Emergency response"
          ],
          "content": "",
          "keywords": [
            "procedures",
            "protocols",
            "discipline",
            "response",
            "handling",
            "range",
            "consciousness",
            "emergency",
            "rules",
            "equipment",
            "safety",
            "command"
          ],
          "page_number": 177
        },
        {
          "name": "Aiming II Alteration of Sight",
          "difficulty": [
            "SD/SW"
          ],
          "topics": [
            "Sight adjustment",
            "Windage correction",
            "Elevation changes",
            "Zero confirmation"
          ],
          "learning_objectives": [
            "Advanced aiming",
            "Sight adjustment skills",
            "Precision shooting"
          ],
          "content": "This section covers advanced sight adjustment, including windage and elevation corrections, and zero confirmation for precision shooting.",
          "keywords": [
            "sight adjustment",
            "windage correction",
            "elevation change",
            "zero confirmation",
            "precision shooting"
          ],
          "page_number": 180
        },
        {
          "name": "Theory of Group and Snap Shooting",
          "difficulty": [
            "SD/SW"
          ],
          "topics": [
            "Group shooting theory",
            "Snap shooting technique",
            "Quick target engagement",
            "Accuracy vs speed"
          ],
          "learning_objectives": [
            "Advanced shooting theory",
            "Quick engagement skills",
            "Tactical shooting"
          ],
          "content": "This section explains the theory behind group shooting and snap shooting, focusing on quick target engagement, balancing accuracy and speed, and tactical application.",
          "keywords": [
            "group shooting",
            "snap shooting",
            "quick engagement",
            "accuracy vs speed",
            "tactical shooting"
          ],
          "page_number": 182
        },
        {
          "name": "Short Range Firing (.22 Rifle), Long/Short Range 7.62mm Rifle Course",
          "difficulty": [
            "JD/JW",
            "SD/SW"
          ],
          "topics": [
            "Firing courses",
            "Range classifications",
            "Scoring systems",
            "Qualification standards"
          ],
          "learning_objectives": [
            "Marksmanship qualification",
            "Course completion",
            "Performance standards"
          ],
          "content": "This section describes short and long range firing courses with .22 and 7.62mm rifles, range classifications, scoring systems, and qualification standards for marksmanship.",
          "keywords": [
            "short range firing",
            "long range firing",
            "firing courses",
            "range classification",
            "scoring system",
            "marksmanship qualification"
          ],
          "page_number": null
        },
        {
          "name": "Characteristics of 7.62 mm SLR and 5.56 mm INSAS",
          "difficulty": [
            "SD/SW"
          ],
          "topics": [
            "SLR specifications",
            "INSAS features",
            "Comparison study",
            "Operational use"
          ],
          "learning_objectives": [
            "Weapon knowledge",
            "Technical understanding",
            "Comparative analysis"
          ],
          "content": "This section compares the characteristics, specifications, and operational use of the 7.62 mm SLR and 5.56 mm INSAS rifles, highlighting technical differences and practical applications.",
          "keywords": [
            "7.62mm SLR",
            "5.56mm INSAS",
            "weapon comparison",
            "specifications",
            "operational use"
          ],
          "page_number": 188
        }
      ],
      "id": "weapon-training"
    },
    {
      "title": "LEADERSHIP",
      "wing": "COMMON",
      "sections": [
        {
          "name": "Motivation",
          "difficulty": [
            "JD/JW",
            "SD/SW"
          ],
          "topics": [
            "Nature of motivation",
            "Types of motivation",
            "Motivation theories",
            "Self-motivation techniques"
          ],
          "learning_objectives": [
            "Understanding motivation",
            "Self-motivation skills",
            "Motivating others"
          ],
          "content": "",
          "keywords": [
            "motivation",
            "techniques",
            "motivating",
            "nature",
            "skills",
            "understanding",
            "types",
            "self-motivation",
            "theories",
            "others"
          ],
          "page_number": 129
        },
        {
          "name": "Discipline and Duty of a Good Citizen",
          "difficulty": [
            "JD/JW",
            "SD/SW"
          ],
          "topics": [
            "Concept of discipline",
            "Types of discipline",
            "Civic duties",
            "Responsible citizenship"
          ],
          "learning_objectives": [
            "Disciplined behavior",
            "Civic responsibility",
            "Good citizenship"
          ],
          "content": "",
          "keywords": [
            "concept",
            "discipline",
            "duties",
            "good",
            "civic",
            "behavior",
            "types",
            "responsible",
            "citizenship",
            "responsibility",
            "disciplined"
          ],
          "page_number": null
        },
        {
          "name": "Leadership Traits",
          "difficulty": [
            "JD/JW",
            "SD/SW"
          ],
          "topics": [
            "Essential leadership qualities",
            "Character traits",
            "Behavioral patterns",
            "Leadership development"
          ],
          "learning_objectives": [
            "Leadership awareness",
            "Self-assessment",
            "Character development"
          ],
          "content": "",
          "keywords": [
            "essential",
            "qualities",
            "patterns",
            "leadership",
            "development",
            "awareness",
            "traits",
            "self-assessment",
            "behavioral",
            "character"
          ],
          "page_number": 133
        },
        {
          "name": "Personality/Character Development",
          "difficulty": [
            "JD/JW",
            "SD/SW"
          ],
          "topics": [
            "Personality formation",
            "Character building",
            "Self-improvement",
            "Value system"
          ],
          "learning_objectives": [
            "Personal growth",
            "Character building",
            "Value development"
          ],
          "content": "",
          "keywords": [
            "personal",
            "value",
            "personality",
            "growth",
            "development",
            "self-improvement",
            "system",
            "character",
            "formation",
            "building"
          ],
          "page_number": null
        },
        {
          "name": "Types of Leadership",
          "difficulty": [
            "SD/SW"
          ],
          "topics": [
            "Leadership styles",
            "Situational leadership",
            "Democratic vs autocratic",
            "Transformational leadership"
          ],
          "learning_objectives": [
            "Leadership styles understanding",
            "Situational adaptation",
            "Effective leadership"
          ],
          "content": "",
          "keywords": [
            "styles",
            "adaptation",
            "democratic",
            "situational",
            "leadership",
            "transformational",
            "understanding",
            "effective",
            "autocratic"
          ],
          "page_number": 140
        },
        {
          "name": "Values/Code of Ethics",
          "difficulty": [
            "SD/SW"
          ],
          "topics": [
            "Moral values",
            "Ethical principles",
            "Code of conduct",
            "Integrity and honesty"
          ],
          "learning_objectives": [
            "Ethical awareness",
            "Moral decision making",
            "Value-based leadership"
          ],
          "content": "",
          "keywords": [
            "integrity",
            "moral",
            "leadership",
            "honesty",
            "awareness",
            "ethical",
            "conduct",
            "making",
            "values",
            "value-based",
            "code",
            "decision",
            "principles"
          ],
          "page_number": 141
        },
        {
          "name": "Perception",
          "difficulty": [
            "SD/SW"
          ],
          "topics": [
            "Perceptual process",
            "Factors affecting perception",
            "Perceptual errors",
            "Improving perception"
          ],
          "learning_objectives": [
            "Understanding perception",
            "Avoiding biases",
            "Better judgment"
          ],
          "content": "",
          "keywords": [
            "improving",
            "factors",
            "judgment",
            "biases",
            "perception",
            "process",
            "understanding",
            "avoiding",
            "perceptual",
            "errors",
            "better",
            "affecting"
          ],
          "page_number": 143
        },
        {
          "name": "Communication Including Inter-personal Communication",
          "difficulty": [
            "SD/SW"
          ],
          "topics": [
            "Communication process",
            "Verbal and non-verbal communication",
            "Listening skills",
            "Interpersonal relations"
          ],
          "learning_objectives": [
            "Effective communication",
            "Interpersonal skills",
            "Better relationships"
          ],
          "content": "",
          "keywords": [
            "better",
            "relationships",
            "verbal",
            "process",
            "non-verbal",
            "listening",
            "skills",
            "effective",
            "interpersonal",
            "communication",
            "relations"
          ],
          "page_number": 147
        },
        {
          "name": "Effect of Leadership with Historical Examples",
          "difficulty": [
            "SD/SW"
          ],
          "topics": [
            "Leadership impact",
            "Historical leaders",
            "Leadership lessons",
            "Case studies"
          ],
          "learning_objectives": [
            "Leadership appreciation",
            "Historical awareness",
            "Learning from examples"
          ],
          "content": "",
          "keywords": [
            "case",
            "lessons",
            "from",
            "examples",
            "appreciation",
            "leadership",
            "historical",
            "awareness",
            "impact",
            "studies",
            "learning",
            "leaders"
          ],
          "page_number": 156
        },
        {
          "name": "Customs of Services",
          "difficulty": [
            "SD/SW"
          ],
          "topics": [
            "Military traditions",
            "Service customs",
            "Ceremonial practices",
            "Honor and dignity"
          ],
          "learning_objectives": [
            "Service appreciation",
            "Traditional values",
            "Military etiquette"
          ],
          "content": "",
          "keywords": [
            "service",
            "ceremonial",
            "dignity",
            "appreciation",
            "etiquette",
            "traditions",
            "practices",
            "customs",
            "values",
            "traditional",
            "military",
            "honor"
          ],
          "page_number": 162
        },
        {
          "name": "Importance of Group/Team Work",
          "difficulty": [
            "SD/SW"
          ],
          "topics": [
            "Team dynamics",
            "Group effectiveness",
            "Cooperation and coordination",
            "Synergy in teams"
          ],
          "learning_objectives": [
            "Teamwork skills",
            "Group leadership",
            "Collaborative success"
          ],
          "content": "",
          "keywords": [
            "team",
            "teams",
            "group",
            "success",
            "effectiveness",
            "coordination",
            "skills",
            "leadership",
            "synergy",
            "teamwork",
            "collaborative",
            "cooperation",
            "dynamics"
          ],
          "page_number": 167
        }
      ],
      "id": "leadership"
    },
    {
      "title": "CIVIL AFFAIRS/DISASTER MANAGEMENT",
      "wing": "COMMON",
      "sections": [
        {
          "name": "Civil Defence Organisation and its Duties",
          "difficulty": [
            "JD/JW",
            "SD/SW"
          ],
          "topics": [
            "Civil defence structure",
            "Organizational duties",
            "Emergency response",
            "Community protection"
          ],
          "learning_objectives": [
            "Understanding civil defence",
            "Emergency preparedness",
            "Community service"
          ],
          "content": "",
          "keywords": [
            "service",
            "defence",
            "duties",
            "response",
            "preparedness",
            "understanding",
            "structure",
            "protection",
            "civil",
            "emergency",
            "community",
            "organizational"
          ],
          "page_number": 173
        },
        {
          "name": "Types of Emergencies/Natural Disasters",
          "difficulty": [
            "JD/JW",
            "SD/SW"
          ],
          "topics": [
            "Natural disasters classification",
            "Man-made emergencies",
            "Disaster characteristics",
            "Risk assessment"
          ],
          "learning_objectives": [
            "Disaster awareness",
            "Risk recognition",
            "Emergency preparedness"
          ],
          "content": "",
          "keywords": [
            "classification",
            "emergencies",
            "man-made",
            "natural",
            "assessment",
            "recognition",
            "preparedness",
            "characteristics",
            "awareness",
            "disasters",
            "risk",
            "emergency",
            "disaster"
          ],
          "page_number": null
        },
        {
          "name": "Fire Fighting",
          "difficulty": [
            "JD/JW",
            "SD/SW"
          ],
          "topics": [
            "Fire triangle concept",
            "Types of fires",
            "Fire extinguishing methods",
            "Fire safety measures"
          ],
          "learning_objectives": [
            "Fire safety knowledge",
            "Emergency response",
            "Prevention techniques"
          ],
          "content": "",
          "keywords": [
            "methods",
            "concept",
            "response",
            "techniques",
            "emergency",
            "types",
            "fire",
            "triangle",
            "knowledge",
            "extinguishing",
            "fires",
            "safety",
            "measures",
            "prevention"
          ],
          "page_number": 178
        },
        {
          "name": "Essential Services and their Maintenance",
          "difficulty": [
            "JD/JW",
            "SD/SW"
          ],
          "topics": [
            "Public utilities",
            "Infrastructure maintenance",
            "Service continuity",
            "Emergency repairs"
          ],
          "learning_objectives": [
            "Infrastructure awareness",
            "Service importance",
            "Maintenance understanding"
          ],
          "content": "",
          "keywords": [
            "infrastructure",
            "service",
            "utilities",
            "public",
            "repairs",
            "emergency",
            "awareness",
            "importance",
            "understanding",
            "maintenance",
            "continuity"
          ],
          "page_number": 182
        },
        {
          "name": "Protection",
          "difficulty": [
            "JD/JW"
          ],
          "topics": [
            "Personal protection",
            "Community safety",
            "Protective equipment",
            "Safety protocols"
          ],
          "learning_objectives": [
            "Safety awareness",
            "Protection methods",
            "Risk mitigation"
          ],
          "content": "",
          "keywords": [
            "equipment",
            "personal",
            "protocols",
            "methods",
            "awareness",
            "risk",
            "protection",
            "mitigation",
            "community",
            "protective",
            "safety"
          ],
          "page_number": 186
        },
        {
          "name": "Role of NCC during Natural Hazards",
          "difficulty": [
            "JD/JW"
          ],
          "topics": [
            "NCC disaster response",
            "Community assistance",
            "Relief operations",
            "Coordination with authorities"
          ],
          "learning_objectives": [
            "Service orientation",
            "Disaster response",
            "Community service"
          ],
          "content": "",
          "keywords": [
            "with",
            "service",
            "response",
            "operations",
            "orientation",
            "assistance",
            "relief",
            "coordination",
            "disaster",
            "community",
            "authorities"
          ],
          "page_number": 193
        },
        {
          "name": "Traffic Control during Disaster under Police Supervision",
          "difficulty": [
            "SD/SW"
          ],
          "topics": [
            "Traffic management",
            "Emergency routing",
            "Coordination with police",
            "Public safety"
          ],
          "learning_objectives": [
            "Traffic control skills",
            "Emergency management",
            "Authority coordination"
          ],
          "content": "",
          "keywords": [
            "with",
            "authority",
            "traffic",
            "public",
            "coordination",
            "routing",
            "skills",
            "control",
            "management",
            "emergency",
            "police",
            "safety"
          ],
          "page_number": 199
        },
        {
          "name": "Disaster Management during Flood/Cyclone",
          "difficulty": [
            "SD/SW"
          ],
          "topics": [
            "Flood response procedures",
            "Cyclone preparedness",
            "Evacuation planning",
            "Relief coordination"
          ],
          "learning_objectives": [
            "Disaster-specific response",
            "Emergency planning",
            "Relief operations"
          ],
          "content": "",
          "keywords": [
            "procedures",
            "evacuation",
            "response",
            "operations",
            "flood",
            "planning",
            "relief",
            "preparedness",
            "coordination",
            "disaster-specific",
            "cyclone",
            "emergency"
          ],
          "page_number": 202
        },
        {
          "name": "Disaster Management during Earth Quake",
          "difficulty": [
            "SD/SW"
          ],
          "topics": [
            "Earthquake preparedness",
            "Response procedures",
            "Search and rescue",
            "Post-earthquake recovery"
          ],
          "learning_objectives": [
            "Earthquake response",
            "Rescue techniques",
            "Recovery planning"
          ],
          "content": "",
          "keywords": [
            "procedures",
            "response",
            "techniques",
            "planning",
            "earthquake",
            "preparedness",
            "recovery",
            "search",
            "rescue",
            "post-earthquake"
          ],
          "page_number": 207
        },
        {
          "name": "Setting up Relief Camp during Disaster Management",
          "difficulty": [
            "SD/SW"
          ],
          "topics": [
            "Camp establishment",
            "Resource management",
            "Hygiene and sanitation",
            "Camp administration"
          ],
          "learning_objectives": [
            "Relief camp management",
            "Resource coordination",
            "Administrative skills"
          ],
          "content": "",
          "keywords": [
            "resource",
            "administrative",
            "relief",
            "coordination",
            "sanitation",
            "skills",
            "camp",
            "administration",
            "establishment",
            "management",
            "hygiene"
          ],
          "page_number": 211
        },
        {
          "name": "Assistance in Removal of Debris",
          "difficulty": [
            "SD/SW"
          ],
          "topics": [
            "Debris clearance",
            "Safety procedures",
            "Equipment usage",
            "Coordination with agencies"
          ],
          "learning_objectives": [
            "Clearance operations",
            "Safety awareness",
            "Team coordination"
          ],
          "content": "",
          "keywords": [
            "agencies",
            "procedures",
            "with",
            "team",
            "operations",
            "coordination",
            "awareness",
            "usage",
            "equipment",
            "safety",
            "debris",
            "clearance"
          ],
          "page_number": null
        },
        {
          "name": "Collection and Distribution of Aid Material",
          "difficulty": [
            "SD/SW"
          ],
          "topics": [
            "Aid collection procedures",
            "Distribution systems",
            "Inventory management",
            "Fair distribution"
          ],
          "learning_objectives": [
            "Relief distribution",
            "Inventory skills",
            "Fair allocation"
          ],
          "content": "",
          "keywords": [
            "systems",
            "procedures",
            "collection",
            "fair",
            "relief",
            "skills",
            "distribution",
            "allocation",
            "management",
            "inventory"
          ],
          "page_number": 219
        },
        {
          "name": "Message Services",
          "difficulty": [
            "SD/SW"
          ],
          "topics": [
            "Communication systems",
            "Message handling",
            "Emergency communications",
            "Information dissemination"
          ],
          "learning_objectives": [
            "Communication skills",
            "Information management",
            "Emergency coordination"
          ],
          "content": "",
          "keywords": [
            "systems",
            "message",
            "dissemination",
            "handling",
            "skills",
            "coordination",
            "information",
            "management",
            "emergency",
            "communications",
            "communication"
          ],
          "page_number": null
        }
      ],
      "id": "civil-affairs-disaster-management"
    },
    {
      "title": "SOCIAL SERVICE",
      "wing": "COMMON",
      "sections": [
        {
          "name": "Weaker Sections of our Society and their Needs",
          "difficulty": [
            "JD/JW",
            "SD/SW"
          ],
          "topics": [
            "Identification of vulnerable groups",
            "Socio-economic challenges",
            "Basic needs assessment",
            "Support mechanisms"
          ],
          "learning_objectives": [
            "Social awareness",
            "Empathy development",
            "Service orientation"
          ],
          "content": "",
          "keywords": [
            "basic",
            "service",
            "vulnerable",
            "socio-economic",
            "orientation",
            "social",
            "identification",
            "assessment",
            "development",
            "empathy",
            "awareness",
            "needs",
            "support",
            "mechanisms",
            "groups",
            "challenges"
          ],
          "page_number": 226
        },
        {
          "name": "Social Service and its Need",
          "difficulty": [
            "JD/JW",
            "SD/SW"
          ],
          "topics": [
            "Importance of social service",
            "Community development",
            "Voluntary service",
            "Social responsibility"
          ],
          "learning_objectives": [
            "Service motivation",
            "Social responsibility",
            "Community engagement"
          ],
          "content": "",
          "keywords": [
            "service",
            "motivation",
            "social",
            "development",
            "importance",
            "voluntary",
            "responsibility",
            "community",
            "engagement"
          ],
          "page_number": 331
        },
        {
          "name": "Family Planning",
          "difficulty": [
            "JD/JW",
            "SD/SW"
          ],
          "topics": [
            "Population awareness",
            "Family planning methods",
            "Health education",
            "Responsible parenthood"
          ],
          "learning_objectives": [
            "Population awareness",
            "Health consciousness",
            "Responsible behavior"
          ],
          "content": "",
          "keywords": [
            "methods",
            "education",
            "planning",
            "behavior",
            "awareness",
            "population",
            "responsible",
            "consciousness",
            "family",
            "health",
            "parenthood"
          ],
          "page_number": 333
        },
        {
          "name": "HIV/AIDS: Causes & Prevention and Contribution of Youth Towards Prevention of AIDS",
          "difficulty": [
            "JD/JW",
            "SD/SW"
          ],
          "topics": [
            "HIV/AIDS awareness",
            "Transmission modes",
            "Prevention strategies",
            "Youth role in prevention"
          ],
          "learning_objectives": [
            "Health awareness",
            "Prevention knowledge",
            "Social responsibility"
          ],
          "content": "",
          "keywords": [
            "transmission",
            "hiv/aids",
            "youth",
            "social",
            "modes",
            "awareness",
            "role",
            "strategies",
            "responsibility",
            "knowledge",
            "health",
            "prevention"
          ],
          "page_number": null
        },
        {
          "name": "Cancer, its Causes and Preventive Measures",
          "difficulty": [
            "JD/JW",
            "SD/SW"
          ],
          "topics": [
            "Cancer types and causes",
            "Risk factors",
            "Prevention methods",
            "Early detection"
          ],
          "learning_objectives": [
            "Health awareness",
            "Prevention consciousness",
            "Healthy lifestyle"
          ],
          "content": "",
          "keywords": [
            "methods",
            "factors",
            "lifestyle",
            "awareness",
            "types",
            "early",
            "risk",
            "detection",
            "causes",
            "consciousness",
            "healthy",
            "health",
            "cancer",
            "prevention"
          ],
          "page_number": 347
        },
        {
          "name": "Contribution of Youth towards Social Welfare",
          "difficulty": [
            "JD/JW",
            "SD/SW"
          ],
          "topics": [
            "Youth power in development",
            "Social initiatives",
            "Community programs",
            "Leadership in service"
          ],
          "learning_objectives": [
            "Youth empowerment",
            "Service leadership",
            "Social impact"
          ],
          "content": "",
          "keywords": [
            "power",
            "service",
            "youth",
            "social",
            "programs",
            "development",
            "initiatives",
            "leadership",
            "empowerment",
            "impact",
            "community"
          ],
          "page_number": 355
        },
        {
          "name": "NGOs and their Contribution to Society",
          "difficulty": [
            "JD/JW"
          ],
          "topics": [
            "NGO role and functions",
            "Social development work",
            "Voluntary organizations",
            "Community partnerships"
          ],
          "learning_objectives": [
            "NGO awareness",
            "Volunteer spirit",
            "Partnership understanding"
          ],
          "content": "",
          "keywords": [
            "volunteer",
            "partnerships",
            "social",
            "work",
            "development",
            "functions",
            "role",
            "awareness",
            "voluntary",
            "understanding",
            "partnership",
            "spirit",
            "community",
            "organizations"
          ],
          "page_number": 322
        },
        {
          "name": "Drug Trafficking and Crime",
          "difficulty": [
            "SD/SW"
          ],
          "topics": [
            "Drug abuse problems",
            "Trafficking networks",
            "Crime prevention",
            "Youth vulnerability"
          ],
          "learning_objectives": [
            "Crime awareness",
            "Prevention knowledge",
            "Social vigilance"
          ],
          "content": "",
          "keywords": [
            "crime",
            "youth",
            "social",
            "problems",
            "vulnerability",
            "drug",
            "trafficking",
            "awareness",
            "abuse",
            "networks",
            "vigilance",
            "knowledge",
            "prevention"
          ],
          "page_number": 356
        }
      ],
      "id": "social-service"
    },
    {
      "title": "HEALTH AND HYGIENE",
      "wing": "COMMON",
      "sections": [
        {
          "name": "Structure and Function of the Human Body",
          "difficulty": [
            "JD/JW",
            "SD/SW"
          ],
          "topics": [
            "Body systems overview",
            "Organ functions",
            "Physiological processes",
            "Health maintenance"
          ],
          "learning_objectives": [
            "Body awareness",
            "Health understanding",
            "Physiological knowledge"
          ],
          "content": "",
          "keywords": [
            "systems",
            "body",
            "processes",
            "physiological",
            "overview",
            "functions",
            "awareness",
            "understanding",
            "maintenance",
            "knowledge",
            "health",
            "organ"
          ],
          "page_number": 363
        },
        {
          "name": "Hygiene and Sanitation",
          "difficulty": [
            "JD/JW",
            "SD/SW"
          ],
          "topics": [
            "Personal hygiene",
            "Environmental sanitation",
            "Disease prevention",
            "Clean habits"
          ],
          "learning_objectives": [
            "Hygiene consciousness",
            "Disease prevention",
            "Healthy practices"
          ],
          "content": "",
          "keywords": [
            "personal",
            "disease",
            "clean",
            "practices",
            "environmental",
            "habits",
            "consciousness",
            "healthy",
            "hygiene",
            "sanitation",
            "prevention"
          ],
          "page_number": 367
        },
        {
          "name": "Preventable Diseases",
          "difficulty": [
            "JD/JW",
            "SD/SW"
          ],
          "topics": [
            "Common preventable diseases",
            "Vaccination importance",
            "Prevention strategies",
            "Public health measures"
          ],
          "learning_objectives": [
            "Disease awareness",
            "Prevention knowledge",
            "Health consciousness"
          ],
          "content": "",
          "keywords": [
            "disease",
            "public",
            "common",
            "vaccination",
            "importance",
            "awareness",
            "strategies",
            "consciousness",
            "preventable",
            "knowledge",
            "diseases",
            "health",
            "measures",
            "prevention"
          ],
          "page_number": 373
        },
        {
          "name": "First Aid in Common Medical Emergencies",
          "difficulty": [
            "JD/JW",
            "SD/SW"
          ],
          "topics": [
            "Emergency first aid",
            "Common medical emergencies",
            "Basic life support",
            "Emergency response"
          ],
          "learning_objectives": [
            "First aid skills",
            "Emergency response",
            "Life-saving techniques"
          ],
          "content": "",
          "keywords": [
            "basic",
            "response",
            "life-saving",
            "emergencies",
            "common",
            "techniques",
            "skills",
            "medical",
            "support",
            "life",
            "emergency",
            "first"
          ],
          "page_number": 374
        },
        {
          "name": "Dressing of Wounds",
          "difficulty": [
            "JD/JW",
            "SD/SW"
          ],
          "topics": [
            "Wound types",
            "Dressing techniques",
            "Infection prevention",
            "Healing process"
          ],
          "learning_objectives": [
            "Wound care skills",
            "Infection prevention",
            "Healing knowledge"
          ],
          "content": "",
          "keywords": [
            "care",
            "techniques",
            "healing",
            "process",
            "skills",
            "types",
            "wound",
            "knowledge",
            "dressing",
            "infection",
            "prevention"
          ],
          "page_number": 388
        },
        {
          "name": "Yoga: Introduction and Exercises",
          "difficulty": [
            "JD/JW",
            "SD/SW"
          ],
          "topics": [
            "Yoga philosophy",
            "Basic yoga exercises",
            "Physical benefits",
            "Mental wellness"
          ],
          "learning_objectives": [
            "Yoga awareness",
            "Physical fitness",
            "Mental wellness"
          ],
          "content": "",
          "keywords": [
            "wellness",
            "basic",
            "exercises",
            "fitness",
            "benefits",
            "philosophy",
            "mental",
            "awareness",
            "yoga",
            "physical"
          ],
          "page_number": 390
        },
        {
          "name": "Physical and Mental Health",
          "difficulty": [
            "SD/SW"
          ],
          "topics": [
            "Physical fitness importance",
            "Mental health awareness",
            "Stress management",
            "Holistic wellness"
          ],
          "learning_objectives": [
            "Holistic health",
            "Stress management",
            "Wellness practices"
          ],
          "content": "",
          "keywords": [
            "holistic",
            "wellness",
            "fitness",
            "stress",
            "importance",
            "awareness",
            "mental",
            "practices",
            "management",
            "health",
            "physical"
          ],
          "page_number": 399
        },
        {
          "name": "Fractures, Types and Treatment",
          "difficulty": [
            "SD/SW"
          ],
          "topics": [
            "Fracture types",
            "First aid for fractures",
            "Immobilization techniques",
            "Emergency care"
          ],
          "learning_objectives": [
            "Fracture recognition",
            "Emergency treatment",
            "Immobilization skills"
          ],
          "content": "",
          "keywords": [
            "techniques",
            "fracture",
            "treatment",
            "recognition",
            "immobilization",
            "skills",
            "types",
            "fractures",
            "emergency",
            "first",
            "care"
          ],
          "page_number": 403
        },
        {
          "name": "Evacuation of Casualties",
          "difficulty": [
            "SD/SW"
          ],
          "topics": [
            "Casualty evacuation methods",
            "Transportation techniques",
            "Safety during evacuation",
            "Team coordination"
          ],
          "learning_objectives": [
            "Evacuation techniques",
            "Safety procedures",
            "Team coordination"
          ],
          "content": "",
          "keywords": [
            "methods",
            "casualty",
            "evacuation",
            "team",
            "techniques",
            "procedures",
            "during",
            "coordination",
            "transportation",
            "safety"
          ],
          "page_number": 410
        }
      ],
      "id": "health-and-hygiene"
    },
    {
      "title": "ADVENTURE ACTIVITIES",
      "wing": "COMMON",
      "sections": [
        {
          "name": "Introduction",
          "difficulty": [
            "JD/JW",
            "SD/SW"
          ],
          "topics": [
            "Adventure activities concept",
            "Benefits and objectives",
            "Safety considerations",
            "Character building"
          ],
          "learning_objectives": [
            "Adventure awareness",
            "Safety consciousness",
            "Character development"
          ],
          "content": "",
          "keywords": [
            "concept",
            "development",
            "benefits",
            "activities",
            "considerations",
            "awareness",
            "objectives",
            "adventure",
            "consciousness",
            "character",
            "safety",
            "building"
          ],
          "page_number": null
        },
        {
          "name": "Trekking",
          "difficulty": [
            "JD/JW",
            "SD/SW"
          ],
          "topics": [
            "Trekking basics",
            "Equipment requirements",
            "Safety measures",
            "Navigation skills"
          ],
          "learning_objectives": [
            "Trekking skills",
            "Outdoor survival",
            "Navigation abilities"
          ],
          "content": "",
          "keywords": [
            "trekking",
            "survival",
            "requirements",
            "skills",
            "navigation",
            "outdoor",
            "abilities",
            "basics",
            "equipment",
            "safety",
            "measures"
          ],
          "page_number": null
        },
        {
          "name": "Cycle Expedition: Planning, Organisation & Conduct",
          "difficulty": [
            "JD/JW"
          ],
          "topics": [
            "Expedition planning",
            "Route selection",
            "Equipment preparation",
            "Safety protocols"
          ],
          "learning_objectives": [
            "Planning skills",
            "Organization abilities",
            "Safety awareness"
          ],
          "content": "",
          "keywords": [
            "protocols",
            "preparation",
            "planning",
            "organization",
            "skills",
            "awareness",
            "expedition",
            "abilities",
            "route",
            "equipment",
            "safety",
            "selection"
          ],
          "page_number": null
        },
        {
          "name": "Para Sailing: Equipment & Conduct",
          "difficulty": [
            "SD/SW"
          ],
          "topics": [
            "Para sailing basics",
            "Equipment knowledge",
            "Safety procedures",
            "Weather considerations"
          ],
          "learning_objectives": [
            "Para sailing awareness",
            "Equipment knowledge",
            "Safety protocols"
          ],
          "content": "",
          "keywords": [
            "procedures",
            "protocols",
            "weather",
            "para",
            "awareness",
            "considerations",
            "basics",
            "knowledge",
            "equipment",
            "safety",
            "sailing"
          ],
          "page_number": null
        }
      ],
      "id": "adventure-activities"
    },
    {
      "title": "ENVIRONMENT AND ECOLOGY",
      "wing": "COMMON",
      "sections": [
        {
          "name": "What is Environment",
          "difficulty": [
            "JD/JW",
            "SD/SW"
          ],
          "topics": [
            "Environmental components",
            "Natural and artificial environment",
            "Environmental systems",
            "Human-environment interaction"
          ],
          "learning_objectives": [
            "Environmental awareness",
            "System understanding",
            "Interaction knowledge"
          ],
          "content": "",
          "keywords": [
            "systems",
            "natural",
            "components",
            "awareness",
            "understanding",
            "environmental",
            "environment",
            "human-environment",
            "system",
            "knowledge",
            "artificial",
            "interaction"
          ],
          "page_number": 415
        },
        {
          "name": "What is Ecology",
          "difficulty": [
            "JD/JW",
            "SD/SW"
          ],
          "topics": [
            "Ecological concepts",
            "Ecosystem components",
            "Food chains and webs",
            "Ecological balance"
          ],
          "learning_objectives": [
            "Ecological understanding",
            "Balance awareness",
            "System knowledge"
          ],
          "content": "",
          "keywords": [
            "chains",
            "concepts",
            "ecosystem",
            "components",
            "webs",
            "understanding",
            "awareness",
            "system",
            "balance",
            "food",
            "ecological",
            "knowledge"
          ],
          "page_number": 418
        },
        {
          "name": "Conservation of Environment and Ecology",
          "difficulty": [
            "JD/JW",
            "SD/SW"
          ],
          "topics": [
            "Conservation importance",
            "Conservation methods",
            "Sustainable practices",
            "Individual responsibility"
          ],
          "learning_objectives": [
            "Conservation awareness",
            "Sustainable practices",
            "Environmental responsibility"
          ],
          "content": "",
          "keywords": [
            "methods",
            "individual",
            "sustainable",
            "importance",
            "practices",
            "awareness",
            "environmental",
            "responsibility",
            "conservation"
          ],
          "page_number": 421
        },
        {
          "name": "Pollution and its Control",
          "difficulty": [
            "JD/JW",
            "SD/SW"
          ],
          "topics": [
            "Types of pollution",
            "Pollution sources",
            "Control measures",
            "Prevention strategies"
          ],
          "learning_objectives": [
            "Pollution awareness",
            "Control knowledge",
            "Prevention skills"
          ],
          "content": "",
          "keywords": [
            "sources",
            "skills",
            "awareness",
            "types",
            "control",
            "strategies",
            "knowledge",
            "pollution",
            "measures",
            "prevention"
          ],
          "page_number": 423
        },
        {
          "name": "Forest Ecology and Pollution",
          "difficulty": [
            "SD/SW"
          ],
          "topics": [
            "Forest ecosystems",
            "Forest importance",
            "Deforestation effects",
            "Forest conservation"
          ],
          "learning_objectives": [
            "Forest awareness",
            "Conservation importance",
            "Environmental impact"
          ],
          "content": "",
          "keywords": [
            "ecosystems",
            "effects",
            "deforestation",
            "importance",
            "awareness",
            "environmental",
            "impact",
            "conservation",
            "forest"
          ],
          "page_number": 305
        },
        {
          "name": "Wild Life",
          "difficulty": [
            "SD/SW"
          ],
          "topics": [
            "Wildlife importance",
            "Biodiversity concepts",
            "Wildlife conservation",
            "Endangered species"
          ],
          "learning_objectives": [
            "Wildlife awareness",
            "Conservation consciousness",
            "Biodiversity appreciation"
          ],
          "content": "",
          "keywords": [
            "species",
            "endangered",
            "concepts",
            "appreciation",
            "biodiversity",
            "importance",
            "awareness",
            "wildlife",
            "consciousness",
            "conservation"
          ],
          "page_number": 307
        }
      ],
      "id": "environment-and-ecology"
    },
    {
      "title": "SELF DEFENCE",
      "wing": "COMMON",
      "sections": [
        {
          "name": "Precaution and General Behavior of Boys/Girls Cadets",
          "difficulty": [
            "JD/JW"
          ],
          "topics": [
            "Safety precautions",
            "Behavioral guidelines",
            "Risk awareness",
            "Personal safety"
          ],
          "learning_objectives": [
            "Safety consciousness",
            "Risk awareness",
            "Preventive behavior"
          ],
          "content": "",
          "keywords": [
            "personal",
            "precautions",
            "behavior",
            "guidelines",
            "awareness",
            "preventive",
            "risk",
            "behavioral",
            "consciousness",
            "safety"
          ],
          "page_number": 432
        },
        {
          "name": "Prevention of Untoward Incidents",
          "difficulty": [
            "JD/JW",
            "SD/SW"
          ],
          "topics": [
            "Incident prevention",
            "Situational awareness",
            "Risk mitigation",
            "Safety strategies"
          ],
          "learning_objectives": [
            "Prevention skills",
            "Awareness development",
            "Safety planning"
          ],
          "content": "",
          "keywords": [
            "situational",
            "planning",
            "skills",
            "development",
            "awareness",
            "risk",
            "incident",
            "strategies",
            "mitigation",
            "safety",
            "prevention"
          ],
          "page_number": 434
        },
        {
          "name": "Vulnerable Parts of the Body",
          "difficulty": [
            "JD/JW",
            "SD/SW"
          ],
          "topics": [
            "Body vulnerability points",
            "Protection methods",
            "Self-defense awareness",
            "Safety techniques"
          ],
          "learning_objectives": [
            "Body awareness",
            "Protection knowledge",
            "Defense understanding"
          ],
          "content": "",
          "keywords": [
            "methods",
            "body",
            "techniques",
            "self-defense",
            "vulnerability",
            "points",
            "awareness",
            "understanding",
            "protection",
            "knowledge",
            "safety",
            "defense"
          ],
          "page_number": 435
        },
        {
          "name": "Physical Self Defence",
          "difficulty": [
            "JD/JW",
            "SD/SW"
          ],
          "topics": [
            "Basic self-defense techniques",
            "Escape methods",
            "Physical defense skills",
            "Emergency response"
          ],
          "learning_objectives": [
            "Self-defense skills",
            "Physical preparedness",
            "Emergency response"
          ],
          "content": "",
          "keywords": [
            "methods",
            "basic",
            "techniques",
            "defense",
            "self-defense",
            "response",
            "preparedness",
            "skills",
            "emergency",
            "physical",
            "escape"
          ],
          "page_number": 437
        }
      ],
      "id": "self-defence"
    },
    {
      "title": "POSTURE TRAINING",
      "wing": "COMMON",
      "sections": [],
      "id": "posture-training"
    },
    {
      "title": "MISCELLANEOUS",
      "wing": "COMMON",
      "sections": [
        {
          "name": "Career Options in Services: Army, Navy & Air Force",
          "difficulty": [
            "JD/JW",
            "SD/SW"
          ],
          "topics": [
            "Military career paths",
            "Service branches overview",
            "Entry requirements",
            "Career progression"
          ],
          "learning_objectives": [
            "Career awareness",
            "Service knowledge",
            "Career planning"
          ],
          "content": "",
          "keywords": [
            "service",
            "progression",
            "requirements",
            "overview",
            "planning",
            "awareness",
            "branches",
            "military",
            "knowledge",
            "entry",
            "paths",
            "career"
          ],
          "page_number": 348
        },
        {
          "name": "Selection Process: WTLOs",
          "difficulty": [
            "JD/JW",
            "SD/SW"
          ],
          "topics": [
            "Selection procedures",
            "WTLO process",
            "Preparation strategies",
            "Assessment criteria"
          ],
          "learning_objectives": [
            "Selection awareness",
            "Preparation knowledge",
            "Process understanding"
          ],
          "content": "",
          "keywords": [
            "procedures",
            "preparation",
            "criteria",
            "process",
            "awareness",
            "understanding",
            "strategies",
            "knowledge",
            "assessment",
            "wtlo",
            "selection"
          ],
          "page_number": null
        },
        {
          "name": "Traffic Rules and Road Signs",
          "difficulty": [
            "JD/JW",
            "SD/SW"
          ],
          "topics": [
            "Traffic regulations",
            "Road sign meanings",
            "Traffic safety",
            "Responsible driving"
          ],
          "learning_objectives": [
            "Traffic awareness",
            "Safety consciousness",
            "Responsible behavior"
          ],
          "content": "",
          "keywords": [
            "road",
            "traffic",
            "meanings",
            "sign",
            "driving",
            "behavior",
            "awareness",
            "responsible",
            "consciousness",
            "regulations",
            "safety"
          ],
          "page_number": 352
        }
      ],
      "id": "miscellaneous"
    }
  ]
}